{"gcc_version": "11.4.0", "files": [{"lines": [{"branches": [], "count": 19, "line_number": 88, "unexecuted_block": false, "function_name": "usage"}, {"branches": [], "count": 19, "line_number": 90, "unexecuted_block": false, "function_name": "usage"}, {"branches": [], "count": 3, "line_number": 91, "unexecuted_block": false, "function_name": "usage"}, {"branches": [], "count": 16, "line_number": 94, "unexecuted_block": false, "function_name": "usage"}, {"branches": [], "count": 16, "line_number": 95, "unexecuted_block": false, "function_name": "usage"}, {"branches": [], "count": 16, "line_number": 100, "unexecuted_block": false, "function_name": "usage"}, {"branches": [], "count": 16, "line_number": 111, "unexecuted_block": false, "function_name": "usage"}, {"branches": [], "count": 16, "line_number": 112, "unexecuted_block": false, "function_name": "usage"}, {"branches": [], "count": 16, "line_number": 113, "unexecuted_block": false, "function_name": "usage"}, {"branches": [], "count": 16, "line_number": 117, "unexecuted_block": false, "function_name": "usage"}, {"branches": [], "count": 19, "line_number": 119, "unexecuted_block": false, "function_name": "usage"}, {"branches": [], "count": 325, "line_number": 123, "unexecuted_block": false, "function_name": "main"}, {"branches": [], "count": 325, "line_number": 126, "unexecuted_block": false, "function_name": "main"}, {"branches": [], "count": 325, "line_number": 127, "unexecuted_block": false, "function_name": "main"}, {"branches": [], "count": 325, "line_number": 130, "unexecuted_block": false, "function_name": "main"}, {"branches": [], "count": 325, "line_number": 131, "unexecuted_block": false, "function_name": "main"}, {"branches": [], "count": 325, "line_number": 132, "unexecuted_block": false, "function_name": "main"}, {"branches": [], "count": 325, "line_number": 133, "unexecuted_block": false, "function_name": "main"}, {"branches": [], "count": 325, "line_number": 135, "unexecuted_block": false, "function_name": "main"}, {"branches": [], "count": 875, "line_number": 137, "unexecuted_block": false, "function_name": "main"}, {"branches": [], "count": 583, "line_number": 139, "unexecuted_block": false, "function_name": "main"}, {"branches": [], "count": 1, "line_number": 141, "unexecuted_block": false, "function_name": "main"}, {"branches": [], "count": 1, "line_number": 143, "unexecuted_block": false, "function_name": "main"}, {"branches": [], "count": 3, "line_number": 145, "unexecuted_block": false, "function_name": "main"}, {"branches": [], "count": 3, "line_number": 153, "unexecuted_block": false, "function_name": "main"}, {"branches": [], "count": 3, "line_number": 154, "unexecuted_block": true, "function_name": "main"}, {"branches": [], "count": 0, "line_number": 157, "unexecuted_block": true, "function_name": "main"}, {"branches": [], "count": 0, "line_number": 158, "unexecuted_block": true, "function_name": "main"}, {"branches": [], "count": 66, "line_number": 160, "unexecuted_block": false, "function_name": "main"}, {"branches": [], "count": 66, "line_number": 161, "unexecuted_block": false, "function_name": "main"}, {"branches": [], "count": 66, "line_number": 162, "unexecuted_block": false, "function_name": "main"}, {"branches": [], "count": 90, "line_number": 163, "unexecuted_block": false, "function_name": "main"}, {"branches": [], "count": 90, "line_number": 164, "unexecuted_block": false, "function_name": "main"}, {"branches": [], "count": 90, "line_number": 165, "unexecuted_block": false, "function_name": "main"}, {"branches": [], "count": 88, "line_number": 166, "unexecuted_block": false, "function_name": "main"}, {"branches": [], "count": 88, "line_number": 167, "unexecuted_block": false, "function_name": "main"}, {"branches": [], "count": 88, "line_number": 168, "unexecuted_block": false, "function_name": "main"}, {"branches": [], "count": 150, "line_number": 169, "unexecuted_block": false, "function_name": "main"}, {"branches": [], "count": 150, "line_number": 170, "unexecuted_block": false, "function_name": "main"}, {"branches": [], "count": 150, "line_number": 171, "unexecuted_block": false, "function_name": "main"}, {"branches": [], "count": 87, "line_number": 172, "unexecuted_block": false, "function_name": "main"}, {"branches": [], "count": 87, "line_number": 173, "unexecuted_block": false, "function_name": "main"}, {"branches": [], "count": 87, "line_number": 174, "unexecuted_block": false, "function_name": "main"}, {"branches": [], "count": 68, "line_number": 175, "unexecuted_block": false, "function_name": "main"}, {"branches": [], "count": 68, "line_number": 176, "unexecuted_block": false, "function_name": "main"}, {"branches": [], "count": 68, "line_number": 177, "unexecuted_block": false, "function_name": "main"}, {"branches": [], "count": 16, "line_number": 178, "unexecuted_block": false, "function_name": "main"}, {"branches": [], "count": 11, "line_number": 179, "unexecuted_block": false, "function_name": "main"}, {"branches": [], "count": 3, "line_number": 180, "unexecuted_block": false, "function_name": "main"}, {"branches": [], "count": 3, "line_number": 181, "unexecuted_block": false, "function_name": "main"}, {"branches": [], "count": 292, "line_number": 185, "unexecuted_block": false, "function_name": "main"}, {"branches": [], "count": 292, "line_number": 187, "unexecuted_block": false, "function_name": "main"}, {"branches": [], "count": 0, "line_number": 188, "unexecuted_block": true, "function_name": "main"}, {"branches": [], "count": 292, "line_number": 191, "unexecuted_block": false, "function_name": "main"}, {"branches": [], "count": 0, "line_number": 192, "unexecuted_block": true, "function_name": "main"}, {"branches": [], "count": 436, "line_number": 194, "unexecuted_block": false, "function_name": "main"}, {"branches": [], "count": 144, "line_number": 195, "unexecuted_block": false, "function_name": "main"}, {"branches": [], "count": 80, "line_number": 196, "unexecuted_block": false, "function_name": "main"}, {"branches": [], "count": 14, "line_number": 197, "unexecuted_block": false, "function_name": "main"}, {"branches": [], "count": 292, "line_number": 199, "unexecuted_block": false, "function_name": "main"}, {"branches": [], "count": 0, "line_number": 200, "unexecuted_block": true, "function_name": "main"}, {"branches": [], "count": 292, "line_number": 203, "unexecuted_block": false, "function_name": "main"}, {"branches": [], "count": 1, "line_number": 204, "unexecuted_block": true, "function_name": "main"}, {"branches": [], "count": 291, "line_number": 212, "unexecuted_block": false, "function_name": "main"}, {"branches": [], "count": 126, "line_number": 213, "unexecuted_block": false, "function_name": "main"}, {"branches": [], "count": 126, "line_number": 214, "unexecuted_block": false, "function_name": "main"}, {"branches": [], "count": 1, "line_number": 217, "unexecuted_block": true, "function_name": "main"}, {"branches": [], "count": 1, "line_number": 218, "unexecuted_block": false, "function_name": "main"}, {"branches": [], "count": 0, "line_number": 219, "unexecuted_block": true, "function_name": "main"}, {"branches": [], "count": 0, "line_number": 220, "unexecuted_block": true, "function_name": "main"}, {"branches": [], "count": 0, "line_number": 221, "unexecuted_block": true, "function_name": "main"}, {"branches": [], "count": 291, "line_number": 224, "unexecuted_block": false, "function_name": "main"}, {"branches": [], "count": 165, "line_number": 226, "unexecuted_block": false, "function_name": "main"}, {"branches": [], "count": 165, "line_number": 231, "unexecuted_block": false, "function_name": "main"}, {"branches": [], "count": 427, "line_number": 233, "unexecuted_block": false, "function_name": "main"}, {"branches": [], "count": 262, "line_number": 235, "unexecuted_block": false, "function_name": "main"}, {"branches": [], "count": 262, "line_number": 236, "unexecuted_block": false, "function_name": "main"}, {"branches": [], "count": 262, "line_number": 237, "unexecuted_block": false, "function_name": "main"}, {"branches": [], "count": 262, "line_number": 241, "unexecuted_block": false, "function_name": "main"}, {"branches": [], "count": 260, "line_number": 243, "unexecuted_block": false, "function_name": "main"}, {"branches": [], "count": 259, "line_number": 244, "unexecuted_block": false, "function_name": "main"}, {"branches": [], "count": 262, "line_number": 246, "unexecuted_block": false, "function_name": "main"}, {"branches": [], "count": 3, "line_number": 248, "unexecuted_block": false, "function_name": "main"}, {"branches": [], "count": 3, "line_number": 249, "unexecuted_block": false, "function_name": "main"}, {"branches": [], "count": 259, "line_number": 253, "unexecuted_block": false, "function_name": "main"}, {"branches": [], "count": 6, "line_number": 254, "unexecuted_block": false, "function_name": "main"}, {"branches": [], "count": 259, "line_number": 255, "unexecuted_block": false, "function_name": "main"}, {"branches": [], "count": 259, "line_number": 256, "unexecuted_block": false, "function_name": "main"}, {"branches": [], "count": 259, "line_number": 257, "unexecuted_block": false, "function_name": "main"}, {"branches": [], "count": 262, "line_number": 259, "unexecuted_block": false, "function_name": "main"}, {"branches": [], "count": 126, "line_number": 267, "unexecuted_block": false, "function_name": "main"}, {"branches": [], "count": 126, "line_number": 268, "unexecuted_block": false, "function_name": "main"}, {"branches": [], "count": 155, "line_number": 270, "unexecuted_block": false, "function_name": "main"}, {"branches": [], "count": 29, "line_number": 271, "unexecuted_block": false, "function_name": "main"}, {"branches": [], "count": 93, "line_number": 273, "unexecuted_block": false, "function_name": "main"}, {"branches": [], "count": 93, "line_number": 274, "unexecuted_block": false, "function_name": "main"}, {"branches": [], "count": 93, "line_number": 275, "unexecuted_block": true, "function_name": "main"}, {"branches": [], "count": 0, "line_number": 276, "unexecuted_block": true, "function_name": "main"}, {"branches": [], "count": 155, "line_number": 279, "unexecuted_block": false, "function_name": "main"}, {"branches": [], "count": 29, "line_number": 280, "unexecuted_block": false, "function_name": "main"}, {"branches": [], "count": 21, "line_number": 282, "unexecuted_block": false, "function_name": "main"}, {"branches": [], "count": 21, "line_number": 283, "unexecuted_block": false, "function_name": "main"}, {"branches": [], "count": 21, "line_number": 284, "unexecuted_block": true, "function_name": "main"}, {"branches": [], "count": 0, "line_number": 285, "unexecuted_block": true, "function_name": "main"}, {"branches": [], "count": 126, "line_number": 288, "unexecuted_block": false, "function_name": "main"}, {"branches": [], "count": 29, "line_number": 290, "unexecuted_block": false, "function_name": "main"}, {"branches": [], "count": 29, "line_number": 291, "unexecuted_block": false, "function_name": "main"}, {"branches": [], "count": 29, "line_number": 292, "unexecuted_block": true, "function_name": "main"}, {"branches": [], "count": 0, "line_number": 293, "unexecuted_block": true, "function_name": "main"}, {"branches": [], "count": 29, "line_number": 295, "unexecuted_block": false, "function_name": "main"}, {"branches": [], "count": 29, "line_number": 296, "unexecuted_block": false, "function_name": "main"}, {"branches": [], "count": 29, "line_number": 297, "unexecuted_block": true, "function_name": "main"}, {"branches": [], "count": 0, "line_number": 298, "unexecuted_block": true, "function_name": "main"}, {"branches": [], "count": 126, "line_number": 300, "unexecuted_block": false, "function_name": "main"}, {"branches": [], "count": 291, "line_number": 303, "unexecuted_block": false, "function_name": "main"}, {"branches": [], "count": 78, "line_number": 310, "unexecuted_block": false, "function_name": "gidtostr_ptr"}, {"branches": [], "count": 78, "line_number": 313, "unexecuted_block": false, "function_name": "gidtostr_ptr"}, {"branches": [], "count": 144, "line_number": 321, "unexecuted_block": false, "function_name": "uidtostr_ptr"}, {"branches": [], "count": 144, "line_number": 324, "unexecuted_block": false, "function_name": "uidtostr_ptr"}, {"branches": [], "count": 180, "line_number": 331, "unexecuted_block": false, "function_name": "print_user"}, {"branches": [], "count": 180, "line_number": 333, "unexecuted_block": false, "function_name": "print_user"}, {"branches": [], "count": 180, "line_number": 335, "unexecuted_block": false, "function_name": "print_user"}, {"branches": [], "count": 47, "line_number": 337, "unexecuted_block": false, "function_name": "print_user"}, {"branches": [], "count": 47, "line_number": 338, "unexecuted_block": false, "function_name": "print_user"}, {"branches": [], "count": 0, "line_number": 340, "unexecuted_block": true, "function_name": "print_user"}, {"branches": [], "count": 0, "line_number": 342, "unexecuted_block": true, "function_name": "print_user"}, {"branches": [], "count": 180, "line_number": 346, "unexecuted_block": false, "function_name": "print_user"}, {"branches": [], "count": 180, "line_number": 347, "unexecuted_block": false, "function_name": "print_user"}, {"branches": [], "count": 180, "line_number": 348, "unexecuted_block": false, "function_name": "print_user"}, {"branches": [], "count": 11, "line_number": 353, "unexecuted_block": false, "function_name": "print_full_info"}, {"branches": [], "count": 11, "line_number": 358, "unexecuted_block": false, "function_name": "print_full_info"}, {"branches": [], "count": 11, "line_number": 359, "unexecuted_block": false, "function_name": "print_full_info"}, {"branches": [], "count": 11, "line_number": 360, "unexecuted_block": false, "function_name": "print_full_info"}, {"branches": [], "count": 11, "line_number": 361, "unexecuted_block": false, "function_name": "print_full_info"}, {"branches": [], "count": 11, "line_number": 363, "unexecuted_block": false, "function_name": "print_full_info"}, {"branches": [], "count": 11, "line_number": 364, "unexecuted_block": false, "function_name": "print_full_info"}, {"branches": [], "count": 11, "line_number": 365, "unexecuted_block": false, "function_name": "print_full_info"}, {"branches": [], "count": 11, "line_number": 366, "unexecuted_block": false, "function_name": "print_full_info"}, {"branches": [], "count": 11, "line_number": 368, "unexecuted_block": false, "function_name": "print_full_info"}, {"branches": [], "count": 0, "line_number": 370, "unexecuted_block": true, "function_name": "print_full_info"}, {"branches": [], "count": 0, "line_number": 371, "unexecuted_block": true, "function_name": "print_full_info"}, {"branches": [], "count": 0, "line_number": 372, "unexecuted_block": true, "function_name": "print_full_info"}, {"branches": [], "count": 0, "line_number": 373, "unexecuted_block": true, "function_name": "print_full_info"}, {"branches": [], "count": 11, "line_number": 376, "unexecuted_block": false, "function_name": "print_full_info"}, {"branches": [], "count": 0, "line_number": 378, "unexecuted_block": true, "function_name": "print_full_info"}, {"branches": [], "count": 0, "line_number": 379, "unexecuted_block": true, "function_name": "print_full_info"}, {"branches": [], "count": 0, "line_number": 380, "unexecuted_block": true, "function_name": "print_full_info"}, {"branches": [], "count": 0, "line_number": 381, "unexecuted_block": true, "function_name": "print_full_info"}, {"branches": [], "count": 11, "line_number": 388, "unexecuted_block": false, "function_name": "print_full_info"}, {"branches": [], "count": 10, "line_number": 389, "unexecuted_block": true, "function_name": "print_full_info"}, {"branches": [], "count": 1, "line_number": 391, "unexecuted_block": false, "function_name": "print_full_info"}, {"branches": [], "count": 11, "line_number": 393, "unexecuted_block": false, "function_name": "print_full_info"}, {"branches": [], "count": 11, "line_number": 394, "unexecuted_block": false, "function_name": "print_full_info"}, {"branches": [], "count": 0, "line_number": 396, "unexecuted_block": true, "function_name": "print_full_info"}, {"branches": [], "count": 0, "line_number": 397, "unexecuted_block": true, "function_name": "print_full_info"}, {"branches": [], "count": 0, "line_number": 400, "unexecuted_block": true, "function_name": "print_full_info"}, {"branches": [], "count": 0, "line_number": 401, "unexecuted_block": true, "function_name": "print_full_info"}, {"branches": [], "count": 0, "line_number": 402, "unexecuted_block": true, "function_name": "print_full_info"}, {"branches": [], "count": 11, "line_number": 405, "unexecuted_block": false, "function_name": "print_full_info"}, {"branches": [], "count": 11, "line_number": 406, "unexecuted_block": false, "function_name": "print_full_info"}, {"branches": [], "count": 78, "line_number": 407, "unexecuted_block": false, "function_name": "print_full_info"}, {"branches": [], "count": 67, "line_number": 409, "unexecuted_block": false, "function_name": "print_full_info"}, {"branches": [], "count": 56, "line_number": 410, "unexecuted_block": false, "function_name": "print_full_info"}, {"branches": [], "count": 67, "line_number": 411, "unexecuted_block": false, "function_name": "print_full_info"}, {"branches": [], "count": 67, "line_number": 412, "unexecuted_block": false, "function_name": "print_full_info"}, {"branches": [], "count": 67, "line_number": 413, "unexecuted_block": false, "function_name": "print_full_info"}, {"branches": [], "count": 67, "line_number": 414, "unexecuted_block": false, "function_name": "print_full_info"}, {"branches": [], "count": 11, "line_number": 416, "unexecuted_block": false, "function_name": "print_full_info"}, {"branches": [], "count": 11, "line_number": 421, "unexecuted_block": false, "function_name": "print_full_info"}, {"branches": [], "count": 0, "line_number": 422, "unexecuted_block": true, "function_name": "print_full_info"}, {"branches": [], "count": 385, "line_number": 428, "unexecuted_block": false, "function_name": "print_stuff"}, {"branches": [], "count": 385, "line_number": 430, "unexecuted_block": false, "function_name": "print_stuff"}, {"branches": [], "count": 180, "line_number": 431, "unexecuted_block": false, "function_name": "print_stuff"}, {"branches": [], "count": 205, "line_number": 438, "unexecuted_block": false, "function_name": "print_stuff"}, {"branches": [], "count": 96, "line_number": 439, "unexecuted_block": false, "function_name": "print_stuff"}, {"branches": [], "count": 109, "line_number": 440, "unexecuted_block": false, "function_name": "print_stuff"}, {"branches": [], "count": 98, "line_number": 441, "unexecuted_block": false, "function_name": "print_stuff"}, {"branches": [], "count": 98, "line_number": 442, "unexecuted_block": false, "function_name": "print_stuff"}, {"branches": [], "count": 11, "line_number": 443, "unexecuted_block": false, "function_name": "print_stuff"}, {"branches": [], "count": 0, "line_number": 444, "unexecuted_block": true, "function_name": "print_stuff"}, {"branches": [], "count": 11, "line_number": 446, "unexecuted_block": false, "function_name": "print_stuff"}, {"branches": [], "count": 385, "line_number": 451, "unexecuted_block": false, "function_name": "print_stuff"}, {"branches": [], "count": 20, "line_number": 453, "unexecuted_block": false, "function_name": "print_stuff"}, {"branches": [], "count": 20, "line_number": 454, "unexecuted_block": false, "function_name": "print_stuff"}, {"branches": [], "count": 365, "line_number": 458, "unexecuted_block": false, "function_name": "print_stuff"}, {"branches": [], "count": 385, "line_number": 460, "unexecuted_block": false, "function_name": "print_stuff"}], "functions": [{"blocks": 10, "end_column": 1, "start_line": 88, "name": "usage", "blocks_executed": 10, "execution_count": 19, "demangled_name": "usage", "start_column": 1, "end_line": 120}, {"blocks": 151, "end_column": 1, "start_line": 123, "name": "main", "blocks_executed": 104, "execution_count": 325, "demangled_name": "main", "start_column": 1, "end_line": 304}, {"blocks": 2, "end_column": 1, "start_line": 310, "name": "gidtostr_ptr", "blocks_executed": 2, "execution_count": 78, "demangled_name": "gidtostr_ptr", "start_column": 1, "end_line": 314}, {"blocks": 2, "end_column": 1, "start_line": 321, "name": "uidtostr_ptr", "blocks_executed": 2, "execution_count": 144, "demangled_name": "uidtostr_ptr", "start_column": 1, "end_line": 325}, {"blocks": 13, "end_column": 1, "start_line": 331, "name": "print_user", "blocks_executed": 8, "execution_count": 180, "demangled_name": "print_user", "start_column": 1, "end_line": 348}, {"blocks": 56, "end_column": 1, "start_line": 353, "name": "print_full_info", "blocks_executed": 33, "execution_count": 11, "demangled_name": "print_full_info", "start_column": 1, "end_line": 423}, {"blocks": 30, "end_column": 1, "start_line": 428, "name": "print_stuff", "blocks_executed": 29, "execution_count": 385, "demangled_name": "print_stuff", "start_column": 1, "end_line": 460}], "file": "/home/luiz/Desktop/coreutils/src/id.c"}, {"lines": [{"branches": [], "count": 7, "line_number": 42, "unexecuted_block": true}, {"branches": [], "count": 3, "line_number": 43, "unexecuted_block": true}], "functions": [], "file": "/usr/include/aarch64-linux-gnu/bits/error.h"}, {"lines": [{"branches": [], "count": 0, "line_number": 24, "unexecuted_block": true, "function_name": "smack_new_label_from_self"}, {"branches": [], "count": 0, "line_number": 26, "unexecuted_block": true, "function_name": "smack_new_label_from_self"}, {"branches": [], "count": 0, "line_number": 30, "unexecuted_block": true, "function_name": "smack_set_label_for_self"}, {"branches": [], "count": 0, "line_number": 32, "unexecuted_block": true, "function_name": "smack_set_label_for_self"}, {"branches": [], "count": 325, "line_number": 37, "unexecuted_block": false, "function_name": "is_smack_enabled"}, {"branches": [], "count": 325, "line_number": 42, "unexecuted_block": false, "function_name": "is_smack_enabled"}], "functions": [{"blocks": 2, "end_column": 1, "start_line": 24, "name": "smack_new_label_from_self", "blocks_executed": 0, "execution_count": 0, "demangled_name": "smack_new_label_from_self", "start_column": 1, "end_line": 27}, {"blocks": 2, "end_column": 1, "start_line": 30, "name": "smack_set_label_for_self", "blocks_executed": 0, "execution_count": 0, "demangled_name": "smack_set_label_for_self", "start_column": 1, "end_line": 33}, {"blocks": 2, "end_column": 1, "start_line": 37, "name": "is_smack_enabled", "blocks_executed": 2, "execution_count": 325, "demangled_name": "is_smack_enabled", "start_column": 1, "end_line": 44}], "file": "/home/luiz/Desktop/coreutils/lib/smack.h"}, {"lines": [{"branches": [], "count": 0, "line_number": 98, "unexecuted_block": true, "function_name": "initialize_exit_failure"}, {"branches": [], "count": 0, "line_number": 100, "unexecuted_block": true, "function_name": "initialize_exit_failure"}, {"branches": [], "count": 0, "line_number": 101, "unexecuted_block": true, "function_name": "initialize_exit_failure"}, {"branches": [], "count": 0, "line_number": 102, "unexecuted_block": true, "function_name": "initialize_exit_failure"}, {"branches": [], "count": 0, "line_number": 158, "unexecuted_block": true, "function_name": "to_uchar"}, {"branches": [], "count": 0, "line_number": 178, "unexecuted_block": true, "function_name": "select_plural"}, {"branches": [], "count": 0, "line_number": 183, "unexecuted_block": true, "function_name": "select_plural"}, {"branches": [], "count": 0, "line_number": 261, "unexecuted_block": true, "function_name": "dot_or_dotdot"}, {"branches": [], "count": 0, "line_number": 263, "unexecuted_block": true, "function_name": "dot_or_dotdot"}, {"branches": [], "count": 0, "line_number": 265, "unexecuted_block": true, "function_name": "dot_or_dotdot"}, {"branches": [], "count": 0, "line_number": 266, "unexecuted_block": true, "function_name": "dot_or_dotdot"}, {"branches": [], "count": 0, "line_number": 269, "unexecuted_block": true, "function_name": "dot_or_dotdot"}, {"branches": [], "count": 0, "line_number": 274, "unexecuted_block": true, "function_name": "readdir_ignoring_dot_and_dotdot"}, {"branches": [], "count": 0, "line_number": 277, "unexecuted_block": true, "function_name": "readdir_ignoring_dot_and_dotdot"}, {"branches": [], "count": 0, "line_number": 278, "unexecuted_block": true, "function_name": "readdir_ignoring_dot_and_dotdot"}, {"branches": [], "count": 0, "line_number": 279, "unexecuted_block": true, "function_name": "readdir_ignoring_dot_and_dotdot"}, {"branches": [], "count": 0, "line_number": 280, "unexecuted_block": true, "function_name": "readdir_ignoring_dot_and_dotdot"}, {"branches": [], "count": 0, "line_number": 294, "unexecuted_block": true, "function_name": "directory_status"}, {"branches": [], "count": 0, "line_number": 299, "unexecuted_block": true, "function_name": "directory_status"}, {"branches": [], "count": 0, "line_number": 303, "unexecuted_block": true, "function_name": "directory_status"}, {"branches": [], "count": 0, "line_number": 304, "unexecuted_block": true, "function_name": "directory_status"}, {"branches": [], "count": 0, "line_number": 306, "unexecuted_block": true, "function_name": "directory_status"}, {"branches": [], "count": 0, "line_number": 307, "unexecuted_block": true, "function_name": "directory_status"}, {"branches": [], "count": 0, "line_number": 309, "unexecuted_block": true, "function_name": "directory_status"}, {"branches": [], "count": 0, "line_number": 310, "unexecuted_block": true, "function_name": "directory_status"}, {"branches": [], "count": 0, "line_number": 311, "unexecuted_block": true, "function_name": "directory_status"}, {"branches": [], "count": 0, "line_number": 314, "unexecuted_block": true, "function_name": "directory_status"}, {"branches": [], "count": 0, "line_number": 315, "unexecuted_block": true, "function_name": "directory_status"}, {"branches": [], "count": 0, "line_number": 316, "unexecuted_block": true, "function_name": "directory_status"}, {"branches": [], "count": 0, "line_number": 317, "unexecuted_block": true, "function_name": "directory_status"}, {"branches": [], "count": 0, "line_number": 318, "unexecuted_block": true, "function_name": "directory_status"}, {"branches": [], "count": 0, "line_number": 459, "unexecuted_block": true, "function_name": "gcd"}, {"branches": [], "count": 0, "line_number": 463, "unexecuted_block": true, "function_name": "gcd"}, {"branches": [], "count": 0, "line_number": 464, "unexecuted_block": true, "function_name": "gcd"}, {"branches": [], "count": 0, "line_number": 465, "unexecuted_block": true, "function_name": "gcd"}, {"branches": [], "count": 0, "line_number": 467, "unexecuted_block": true, "function_name": "gcd"}, {"branches": [], "count": 0, "line_number": 469, "unexecuted_block": true, "function_name": "gcd"}, {"branches": [], "count": 0, "line_number": 478, "unexecuted_block": true, "function_name": "lcm"}, {"branches": [], "count": 0, "line_number": 480, "unexecuted_block": true, "function_name": "lcm"}, {"branches": [], "count": 0, "line_number": 489, "unexecuted_block": true, "function_name": "ptr_align"}, {"branches": [], "count": 0, "line_number": 491, "unexecuted_block": true, "function_name": "ptr_align"}, {"branches": [], "count": 0, "line_number": 492, "unexecuted_block": true, "function_name": "ptr_align"}, {"branches": [], "count": 0, "line_number": 493, "unexecuted_block": true, "function_name": "ptr_align"}, {"branches": [], "count": 0, "line_number": 501, "unexecuted_block": true, "function_name": "is_nul"}, {"branches": [], "count": 0, "line_number": 503, "unexecuted_block": true, "function_name": "is_nul"}, {"branches": [], "count": 0, "line_number": 516, "unexecuted_block": true, "function_name": "is_nul"}, {"branches": [], "count": 0, "line_number": 517, "unexecuted_block": true, "function_name": "is_nul"}, {"branches": [], "count": 0, "line_number": 520, "unexecuted_block": true, "function_name": "is_nul"}, {"branches": [], "count": 0, "line_number": 533, "unexecuted_block": true, "function_name": "is_nul"}, {"branches": [], "count": 0, "line_number": 534, "unexecuted_block": true, "function_name": "is_nul"}, {"branches": [], "count": 0, "line_number": 535, "unexecuted_block": true, "function_name": "is_nul"}, {"branches": [], "count": 0, "line_number": 536, "unexecuted_block": true, "function_name": "is_nul"}, {"branches": [], "count": 0, "line_number": 537, "unexecuted_block": true, "function_name": "is_nul"}, {"branches": [], "count": 0, "line_number": 538, "unexecuted_block": true, "function_name": "is_nul"}, {"branches": [], "count": 0, "line_number": 539, "unexecuted_block": true, "function_name": "is_nul"}, {"branches": [], "count": 0, "line_number": 540, "unexecuted_block": true, "function_name": "is_nul"}, {"branches": [], "count": 0, "line_number": 541, "unexecuted_block": true, "function_name": "is_nul"}, {"branches": [], "count": 0, "line_number": 545, "unexecuted_block": true, "function_name": "is_nul"}, {"branches": [], "count": 0, "line_number": 557, "unexecuted_block": true, "function_name": "emit_stdin_note"}, {"branches": [], "count": 0, "line_number": 559, "unexecuted_block": true, "function_name": "emit_stdin_note"}, {"branches": [], "count": 0, "line_number": 562, "unexecuted_block": true, "function_name": "emit_stdin_note"}, {"branches": [], "count": 0, "line_number": 564, "unexecuted_block": true, "function_name": "emit_mandatory_arg_note"}, {"branches": [], "count": 0, "line_number": 566, "unexecuted_block": true, "function_name": "emit_mandatory_arg_note"}, {"branches": [], "count": 0, "line_number": 569, "unexecuted_block": true, "function_name": "emit_mandatory_arg_note"}, {"branches": [], "count": 0, "line_number": 572, "unexecuted_block": true, "function_name": "emit_size_note"}, {"branches": [], "count": 0, "line_number": 574, "unexecuted_block": true, "function_name": "emit_size_note"}, {"branches": [], "count": 0, "line_number": 579, "unexecuted_block": true, "function_name": "emit_size_note"}, {"branches": [], "count": 0, "line_number": 582, "unexecuted_block": true, "function_name": "emit_blocksize_note"}, {"branches": [], "count": 0, "line_number": 584, "unexecuted_block": true, "function_name": "emit_blocksize_note"}, {"branches": [], "count": 0, "line_number": 589, "unexecuted_block": true, "function_name": "emit_blocksize_note"}, {"branches": [], "count": 0, "line_number": 592, "unexecuted_block": true, "function_name": "emit_update_parameters_note"}, {"branches": [], "count": 0, "line_number": 594, "unexecuted_block": true, "function_name": "emit_update_parameters_note"}, {"branches": [], "count": 0, "line_number": 606, "unexecuted_block": true, "function_name": "emit_update_parameters_note"}, {"branches": [], "count": 0, "line_number": 609, "unexecuted_block": true, "function_name": "emit_backup_suffix_note"}, {"branches": [], "count": 0, "line_number": 611, "unexecuted_block": true, "function_name": "emit_backup_suffix_note"}, {"branches": [], "count": 0, "line_number": 618, "unexecuted_block": true, "function_name": "emit_backup_suffix_note"}, {"branches": [], "count": 0, "line_number": 624, "unexecuted_block": true, "function_name": "emit_backup_suffix_note"}, {"branches": [], "count": 0, "line_number": 627, "unexecuted_block": true, "function_name": "emit_symlink_recurse_options"}, {"branches": [], "count": 0, "line_number": 629, "unexecuted_block": true, "function_name": "emit_symlink_recurse_options"}, {"branches": [], "count": 0, "line_number": 642, "unexecuted_block": true, "function_name": "emit_symlink_recurse_options"}, {"branches": [], "count": 0, "line_number": 645, "unexecuted_block": true, "function_name": "emit_exec_status"}, {"branches": [], "count": 0, "line_number": 647, "unexecuted_block": true, "function_name": "emit_exec_status"}, {"branches": [], "count": 0, "line_number": 654, "unexecuted_block": true, "function_name": "emit_exec_status"}, {"branches": [], "count": 16, "line_number": 657, "unexecuted_block": false, "function_name": "emit_ancillary_info"}, {"branches": [], "count": 16, "line_number": 659, "unexecuted_block": false, "function_name": "emit_ancillary_info"}, {"branches": [], "count": 16, "line_number": 669, "unexecuted_block": false, "function_name": "emit_ancillary_info"}, {"branches": [], "count": 16, "line_number": 670, "unexecuted_block": false, "function_name": "emit_ancillary_info"}, {"branches": [], "count": 112, "line_number": 672, "unexecuted_block": false, "function_name": "emit_ancillary_info"}, {"branches": [], "count": 96, "line_number": 673, "unexecuted_block": false, "function_name": "emit_ancillary_info"}, {"branches": [], "count": 16, "line_number": 675, "unexecuted_block": false, "function_name": "emit_ancillary_info"}, {"branches": [], "count": 0, "line_number": 676, "unexecuted_block": true, "function_name": "emit_ancillary_info"}, {"branches": [], "count": 16, "line_number": 678, "unexecuted_block": false, "function_name": "emit_ancillary_info"}, {"branches": [], "count": 16, "line_number": 682, "unexecuted_block": false, "function_name": "emit_ancillary_info"}, {"branches": [], "count": 16, "line_number": 683, "unexecuted_block": false, "function_name": "emit_ancillary_info"}, {"branches": [], "count": 16, "line_number": 689, "unexecuted_block": false, "function_name": "emit_ancillary_info"}, {"branches": [], "count": 16, "line_number": 695, "unexecuted_block": true, "function_name": "emit_ancillary_info"}, {"branches": [], "count": 16, "line_number": 696, "unexecuted_block": false, "function_name": "emit_ancillary_info"}, {"branches": [], "count": 16, "line_number": 698, "unexecuted_block": true, "function_name": "emit_ancillary_info"}, {"branches": [], "count": 16, "line_number": 700, "unexecuted_block": false, "function_name": "emit_ancillary_info"}, {"branches": [], "count": 0, "line_number": 717, "unexecuted_block": true, "function_name": "timetostr"}, {"branches": [], "count": 0, "line_number": 721, "unexecuted_block": true, "function_name": "timetostr"}, {"branches": [], "count": 0, "line_number": 725, "unexecuted_block": true, "function_name": "bad_cast"}, {"branches": [], "count": 0, "line_number": 727, "unexecuted_block": true, "function_name": "bad_cast"}, {"branches": [], "count": 0, "line_number": 732, "unexecuted_block": true, "function_name": "usable_st_size"}, {"branches": [], "count": 0, "line_number": 734, "unexecuted_block": true, "function_name": "usable_st_size"}, {"branches": [], "count": 0, "line_number": 735, "unexecuted_block": true, "function_name": "usable_st_size"}, {"branches": [], "count": 0, "line_number": 767, "unexecuted_block": true, "function_name": "write_error"}, {"branches": [], "count": 0, "line_number": 769, "unexecuted_block": true, "function_name": "write_error"}, {"branches": [], "count": 0, "line_number": 770, "unexecuted_block": true, "function_name": "write_error"}, {"branches": [], "count": 0, "line_number": 771, "unexecuted_block": true, "function_name": "write_error"}, {"branches": [], "count": 0, "line_number": 772, "unexecuted_block": true, "function_name": "write_error"}, {"branches": [], "count": 0, "line_number": 773, "unexecuted_block": true, "function_name": "write_error"}, {"branches": [], "count": 0, "line_number": 782, "unexecuted_block": true, "function_name": "stzncpy"}, {"branches": [], "count": 0, "line_number": 785, "unexecuted_block": true, "function_name": "stzncpy"}, {"branches": [], "count": 0, "line_number": 786, "unexecuted_block": true, "function_name": "stzncpy"}, {"branches": [], "count": 0, "line_number": 787, "unexecuted_block": true, "function_name": "stzncpy"}, {"branches": [], "count": 0, "line_number": 788, "unexecuted_block": true, "function_name": "stzncpy"}, {"branches": [], "count": 0, "line_number": 800, "unexecuted_block": true, "function_name": "is_ENOTSUP"}, {"branches": [], "count": 0, "line_number": 802, "unexecuted_block": true, "function_name": "is_ENOTSUP"}], "functions": [{"blocks": 3, "end_column": 1, "start_line": 98, "name": "initialize_exit_failure", "blocks_executed": 0, "execution_count": 0, "demangled_name": "initialize_exit_failure", "start_column": 1, "end_line": 102}, {"blocks": 2, "end_column": 61, "start_line": 158, "name": "to_uchar", "blocks_executed": 0, "execution_count": 0, "demangled_name": "to_uchar", "start_column": 29, "end_line": 158}, {"blocks": 2, "end_column": 1, "start_line": 178, "name": "select_plural", "blocks_executed": 0, "execution_count": 0, "demangled_name": "select_plural", "start_column": 1, "end_line": 184}, {"blocks": 11, "end_column": 1, "start_line": 261, "name": "dot_or_dotdot", "blocks_executed": 0, "execution_count": 0, "demangled_name": "dot_or_dotdot", "start_column": 1, "end_line": 270}, {"blocks": 7, "end_column": 1, "start_line": 274, "name": "readdir_ignoring_dot_and_dotdot", "blocks_executed": 0, "execution_count": 0, "demangled_name": "readdir_ignoring_dot_and_dotdot", "start_column": 1, "end_line": 282}, {"blocks": 15, "end_column": 1, "start_line": 294, "name": "directory_status", "blocks_executed": 0, "execution_count": 0, "demangled_name": "directory_status", "start_column": 1, "end_line": 319}, {"blocks": 3, "end_column": 1, "start_line": 459, "name": "gcd", "blocks_executed": 0, "execution_count": 0, "demangled_name": "gcd", "start_column": 1, "end_line": 470}, {"blocks": 2, "end_column": 1, "start_line": 478, "name": "lcm", "blocks_executed": 0, "execution_count": 0, "demangled_name": "lcm", "start_column": 1, "end_line": 481}, {"blocks": 2, "end_column": 1, "start_line": 489, "name": "ptr_align", "blocks_executed": 0, "execution_count": 0, "demangled_name": "ptr_align", "start_column": 1, "end_line": 494}, {"blocks": 13, "end_column": 1, "start_line": 501, "name": "is_nul", "blocks_executed": 0, "execution_count": 0, "demangled_name": "is_nul", "start_column": 1, "end_line": 546}, {"blocks": 2, "end_column": 1, "start_line": 557, "name": "emit_stdin_note", "blocks_executed": 0, "execution_count": 0, "demangled_name": "emit_stdin_note", "start_column": 1, "end_line": 562}, {"blocks": 2, "end_column": 1, "start_line": 564, "name": "emit_mandatory_arg_note", "blocks_executed": 0, "execution_count": 0, "demangled_name": "emit_mandatory_arg_note", "start_column": 1, "end_line": 569}, {"blocks": 2, "end_column": 1, "start_line": 572, "name": "emit_size_note", "blocks_executed": 0, "execution_count": 0, "demangled_name": "emit_size_note", "start_column": 1, "end_line": 579}, {"blocks": 2, "end_column": 1, "start_line": 582, "name": "emit_blocksize_note", "blocks_executed": 0, "execution_count": 0, "demangled_name": "emit_blocksize_note", "start_column": 1, "end_line": 589}, {"blocks": 2, "end_column": 1, "start_line": 592, "name": "emit_update_parameters_note", "blocks_executed": 0, "execution_count": 0, "demangled_name": "emit_update_parameters_note", "start_column": 1, "end_line": 606}, {"blocks": 3, "end_column": 1, "start_line": 609, "name": "emit_backup_suffix_note", "blocks_executed": 0, "execution_count": 0, "demangled_name": "emit_backup_suffix_note", "start_column": 1, "end_line": 624}, {"blocks": 2, "end_column": 1, "start_line": 627, "name": "emit_symlink_recurse_options", "blocks_executed": 0, "execution_count": 0, "demangled_name": "emit_symlink_recurse_options", "start_column": 1, "end_line": 642}, {"blocks": 2, "end_column": 1, "start_line": 645, "name": "emit_exec_status", "blocks_executed": 0, "execution_count": 0, "demangled_name": "emit_exec_status", "start_column": 1, "end_line": 654}, {"blocks": 20, "end_column": 1, "start_line": 657, "name": "emit_ancillary_info", "blocks_executed": 17, "execution_count": 16, "demangled_name": "emit_ancillary_info", "start_column": 1, "end_line": 700}, {"blocks": 2, "end_column": 1, "start_line": 717, "name": "timetostr", "blocks_executed": 0, "execution_count": 0, "demangled_name": "timetostr", "start_column": 1, "end_line": 722}, {"blocks": 2, "end_column": 1, "start_line": 725, "name": "bad_cast", "blocks_executed": 0, "execution_count": 0, "demangled_name": "bad_cast", "start_column": 1, "end_line": 728}, {"blocks": 6, "end_column": 1, "start_line": 732, "name": "usable_st_size", "blocks_executed": 0, "execution_count": 0, "demangled_name": "usable_st_size", "start_column": 1, "end_line": 736}, {"blocks": 7, "end_column": 1, "start_line": 767, "name": "write_error", "blocks_executed": 0, "execution_count": 0, "demangled_name": "write_error", "start_column": 1, "end_line": 774}, {"blocks": 6, "end_column": 1, "start_line": 782, "name": "stzncpy", "blocks_executed": 0, "execution_count": 0, "demangled_name": "stzncpy", "start_column": 1, "end_line": 789}, {"blocks": 2, "end_column": 1, "start_line": 800, "name": "is_ENOTSUP", "blocks_executed": 0, "execution_count": 0, "demangled_name": "is_ENOTSUP", "start_column": 1, "end_line": 803}], "file": "/home/luiz/Desktop/coreutils/src/system.h"}, {"lines": [{"branches": [], "count": 0, "line_number": 149, "unexecuted_block": true, "function_name": "pgettext_aux"}, {"branches": [], "count": 0, "line_number": 153, "unexecuted_block": true, "function_name": "pgettext_aux"}, {"branches": [], "count": 0, "line_number": 154, "unexecuted_block": true, "function_name": "pgettext_aux"}, {"branches": [], "count": 0, "line_number": 155, "unexecuted_block": true, "function_name": "pgettext_aux"}, {"branches": [], "count": 0, "line_number": 157, "unexecuted_block": true, "function_name": "pgettext_aux"}, {"branches": [], "count": 0, "line_number": 168, "unexecuted_block": true, "function_name": "npgettext_aux"}, {"branches": [], "count": 0, "line_number": 174, "unexecuted_block": true, "function_name": "npgettext_aux"}, {"branches": [], "count": 0, "line_number": 175, "unexecuted_block": true, "function_name": "npgettext_aux"}, {"branches": [], "count": 0, "line_number": 176, "unexecuted_block": true, "function_name": "npgettext_aux"}, {"branches": [], "count": 0, "line_number": 178, "unexecuted_block": true, "function_name": "npgettext_aux"}, {"branches": [], "count": 0, "line_number": 218, "unexecuted_block": true, "function_name": "dcpgettext_expr"}, {"branches": [], "count": 0, "line_number": 222, "unexecuted_block": true, "function_name": "dcpgettext_expr"}, {"branches": [], "count": 0, "line_number": 223, "unexecuted_block": true, "function_name": "dcpgettext_expr"}, {"branches": [], "count": 0, "line_number": 229, "unexecuted_block": true, "function_name": "dcpgettext_expr"}, {"branches": [], "count": 0, "line_number": 230, "unexecuted_block": true, "function_name": "dcpgettext_expr"}, {"branches": [], "count": 0, "line_number": 232, "unexecuted_block": true, "function_name": "dcpgettext_expr"}, {"branches": [], "count": 0, "line_number": 233, "unexecuted_block": true, "function_name": "dcpgettext_expr"}, {"branches": [], "count": 0, "line_number": 237, "unexecuted_block": true, "function_name": "dcpgettext_expr"}, {"branches": [], "count": 0, "line_number": 238, "unexecuted_block": true, "function_name": "dcpgettext_expr"}, {"branches": [], "count": 0, "line_number": 239, "unexecuted_block": true, "function_name": "dcpgettext_expr"}, {"branches": [], "count": 0, "line_number": 240, "unexecuted_block": true, "function_name": "dcpgettext_expr"}, {"branches": [], "count": 0, "line_number": 241, "unexecuted_block": true, "function_name": "dcpgettext_expr"}, {"branches": [], "count": 0, "line_number": 243, "unexecuted_block": true, "function_name": "dcpgettext_expr"}, {"branches": [], "count": 0, "line_number": 244, "unexecuted_block": true, "function_name": "dcpgettext_expr"}, {"branches": [], "count": 0, "line_number": 246, "unexecuted_block": true, "function_name": "dcpgettext_expr"}, {"branches": [], "count": 0, "line_number": 247, "unexecuted_block": true, "function_name": "dcpgettext_expr"}, {"branches": [], "count": 0, "line_number": 249, "unexecuted_block": true, "function_name": "dcpgettext_expr"}, {"branches": [], "count": 0, "line_number": 265, "unexecuted_block": true, "function_name": "dcnpgettext_expr"}, {"branches": [], "count": 0, "line_number": 270, "unexecuted_block": true, "function_name": "dcnpgettext_expr"}, {"branches": [], "count": 0, "line_number": 271, "unexecuted_block": true, "function_name": "dcnpgettext_expr"}, {"branches": [], "count": 0, "line_number": 277, "unexecuted_block": true, "function_name": "dcnpgettext_expr"}, {"branches": [], "count": 0, "line_number": 278, "unexecuted_block": true, "function_name": "dcnpgettext_expr"}, {"branches": [], "count": 0, "line_number": 280, "unexecuted_block": true, "function_name": "dcnpgettext_expr"}, {"branches": [], "count": 0, "line_number": 281, "unexecuted_block": true, "function_name": "dcnpgettext_expr"}, {"branches": [], "count": 0, "line_number": 285, "unexecuted_block": true, "function_name": "dcnpgettext_expr"}, {"branches": [], "count": 0, "line_number": 286, "unexecuted_block": true, "function_name": "dcnpgettext_expr"}, {"branches": [], "count": 0, "line_number": 287, "unexecuted_block": true, "function_name": "dcnpgettext_expr"}, {"branches": [], "count": 0, "line_number": 288, "unexecuted_block": true, "function_name": "dcnpgettext_expr"}, {"branches": [], "count": 0, "line_number": 289, "unexecuted_block": true, "function_name": "dcnpgettext_expr"}, {"branches": [], "count": 0, "line_number": 291, "unexecuted_block": true, "function_name": "dcnpgettext_expr"}, {"branches": [], "count": 0, "line_number": 292, "unexecuted_block": true, "function_name": "dcnpgettext_expr"}, {"branches": [], "count": 0, "line_number": 294, "unexecuted_block": true, "function_name": "dcnpgettext_expr"}, {"branches": [], "count": 0, "line_number": 295, "unexecuted_block": true, "function_name": "dcnpgettext_expr"}, {"branches": [], "count": 0, "line_number": 297, "unexecuted_block": true, "function_name": "dcnpgettext_expr"}], "functions": [{"blocks": 4, "end_column": 1, "start_line": 149, "name": "pgettext_aux", "blocks_executed": 0, "execution_count": 0, "demangled_name": "pgettext_aux", "start_column": 1, "end_line": 158}, {"blocks": 9, "end_column": 1, "start_line": 168, "name": "npgettext_aux", "blocks_executed": 0, "execution_count": 0, "demangled_name": "npgettext_aux", "start_column": 1, "end_line": 179}, {"blocks": 11, "end_column": 1, "start_line": 218, "name": "dcpgettext_expr", "blocks_executed": 0, "execution_count": 0, "demangled_name": "dcpgettext_expr", "start_column": 1, "end_line": 250}, {"blocks": 19, "end_column": 1, "start_line": 265, "name": "dcnpgettext_expr", "blocks_executed": 0, "execution_count": 0, "demangled_name": "dcnpgettext_expr", "start_column": 1, "end_line": 298}], "file": "/home/luiz/Desktop/coreutils/lib/gettext.h"}, {"lines": [{"branches": [], "count": 0, "line_number": 33, "unexecuted_block": true, "function_name": "__uint16_identity"}, {"branches": [], "count": 0, "line_number": 35, "unexecuted_block": true, "function_name": "__uint16_identity"}, {"branches": [], "count": 0, "line_number": 39, "unexecuted_block": true, "function_name": "__uint32_identity"}, {"branches": [], "count": 0, "line_number": 41, "unexecuted_block": true, "function_name": "__uint32_identity"}, {"branches": [], "count": 0, "line_number": 45, "unexecuted_block": true, "function_name": "__uint64_identity"}, {"branches": [], "count": 0, "line_number": 47, "unexecuted_block": true, "function_name": "__uint64_identity"}], "functions": [{"blocks": 2, "end_column": 1, "start_line": 33, "name": "__uint16_identity", "blocks_executed": 0, "execution_count": 0, "demangled_name": "__uint16_identity", "start_column": 1, "end_line": 36}, {"blocks": 2, "end_column": 1, "start_line": 39, "name": "__uint32_identity", "blocks_executed": 0, "execution_count": 0, "demangled_name": "__uint32_identity", "start_column": 1, "end_line": 42}, {"blocks": 2, "end_column": 1, "start_line": 45, "name": "__uint64_identity", "blocks_executed": 0, "execution_count": 0, "demangled_name": "__uint64_identity", "start_column": 1, "end_line": 48}], "file": "/usr/include/aarch64-linux-gnu/bits/uintn-identity.h"}, {"lines": [{"branches": [], "count": 0, "line_number": 34, "unexecuted_block": true, "function_name": "__bswap_16"}, {"branches": [], "count": 0, "line_number": 37, "unexecuted_block": true, "function_name": "__bswap_16"}, {"branches": [], "count": 0, "line_number": 49, "unexecuted_block": true, "function_name": "__bswap_32"}, {"branches": [], "count": 0, "line_number": 52, "unexecuted_block": true, "function_name": "__bswap_32"}, {"branches": [], "count": 0, "line_number": 70, "unexecuted_block": true, "function_name": "__bswap_64"}, {"branches": [], "count": 0, "line_number": 73, "unexecuted_block": true, "function_name": "__bswap_64"}], "functions": [{"blocks": 2, "end_column": 1, "start_line": 34, "name": "__bswap_16", "blocks_executed": 0, "execution_count": 0, "demangled_name": "__bswap_16", "start_column": 1, "end_line": 41}, {"blocks": 2, "end_column": 1, "start_line": 49, "name": "__bswap_32", "blocks_executed": 0, "execution_count": 0, "demangled_name": "__bswap_32", "start_column": 1, "end_line": 56}, {"blocks": 2, "end_column": 1, "start_line": 70, "name": "__bswap_64", "blocks_executed": 0, "execution_count": 0, "demangled_name": "__bswap_64", "start_column": 1, "end_line": 77}], "file": "/usr/include/aarch64-linux-gnu/bits/byteswap.h"}], "format_version": "1", "current_working_directory": "/home/luiz/Desktop/coreutils", "data_file": "src/id"}